aor/__init__.py
aor/__main__.py
aor/add.py
aor/cli.py
aor/deploy.py
aor/execute.py
aor/lint.py
aor/login.py
aor/new.py
aor/publish.py
aor/resolve.py
aor/rm.py
aor/version.py
aor/agent_management/__init__.py
aor/agent_management/code_generator.py
aor/agent_management/config_manager.py
aor/agent_management/context.py
aor/agent_management/dependency_manager.py
aor/agent_management/input_output_manager.py
aor/agent_management/path_manager.py
aor/agent_management/types.py
aor/agent_management/validation_utils.py
aor/backend/__init__.py
aor/backend/application.py
aor/backend/config.py
aor/backend/endpoint.py
aor/backend/exceptions.py
aor/backend/execute.py
aor/backend/login.py
aor/backend/request.py
aor/backend/resolve.py
aor/backend/response.py
aor/common/__init__.py
aor/common/agent.py
aor/common/config.py
aor/deployment/__init__.py
aor/deployment/agent.py
aor/deployment/base.py
aor/deployment/exceptions.py
aor/deployment/models.py
aor/deployment/clients/__init__.py
aor/deployment/clients/aws/__init__.py
aor/deployment/clients/aws/lambda_client.py
aor/deployment/clients/aws/lambda_deployment.py
aor/deployment/clients/aws/sam_client.py
aor/deployment/utils/__init__.py
aor/deployment/utils/command.py
aor/deployment/utils/config.py
aor/deployment/utils/file_preparation.py
aor/deployment/utils/fs.py
aor/deployment/utils/packaging.py
aor/schema/aionrails.advertise.json
aor/schema/aionrails.deploy.json
aor/schema/aionrails.execute.json
aor/schema/aionrails.full.json
aor/schema/aionrails.json
aor/schema/aionrails.publish.json
aor/schema/openapi.yaml
aor/system/__init__.py
aor/system/credentials.py
aor/system/token.py
aor/templates/__init__.py
aor/templates/components/__init__.py
aor/templates/components/auth/__init__.py
aor/templates/components/auth/api_key.py
aor/templates/components/auth/jwt.py
aor/templates/components/media/__init__.py
aor/templates/components/media/handlers.py
aor/templates/components/media/models.py
aor/templates/components/monitoring/__init__.py
aor-0.2.3.dist-info/METADATA
aor-0.2.3.dist-info/WHEEL
aor-0.2.3.dist-info/entry_points.txt
aor-0.2.3.dist-info/top_level.txt
aor-0.2.3.dist-info/RECORD
