Metadata-Version: 2.4
Name: aor
Version: 0.2.3
Summary: AI-on-Rails: A Python library for prototyping and publishing AI applications with guardrails.
Project-URL: Homepage, https://aionrails.com
Requires-Python: >=3.10
Requires-Dist: boto3>=1.37.32
Requires-Dist: click>=8.1.8
Requires-Dist: fastjsonschema>=2.21.1
Requires-Dist: poetry>=2.1.2
Requires-Dist: requests>=2.32.3
Requires-Dist: requests-toolbelt>=1.0.0
Requires-Dist: rich-click>=1.8.8
Requires-Dist: ruamel-yaml>=0.18.10
Requires-Dist: fastapi>=0.95.0
Requires-Dist: uvicorn>=0.21.0
Requires-Dist: pydantic>=2.0.0
Requires-Dist: langgraph>=0.0.26
Requires-Dist: anthropic>=0.8.0
Requires-Dist: jinja2<4.0.0,>=3.1.6
Requires-Dist: aiohttp>=3.8.0
Requires-Dist: typing-extensions>=4.5.0
Requires-Dist: langchain<0.4.0,>=0.3.24
Requires-Dist: langchain-anthropic<0.4.0,>=0.3.12
Requires-Dist: rich>=13.6.0
Provides-Extra: test
Requires-Dist: pytest>=8.3.5; extra == "test"
Requires-Dist: pytest-cov>=6.1.1; extra == "test"
Provides-Extra: dev
Requires-Dist: black>=25.1.0; extra == "dev"
Requires-Dist: isort>=6.0.1; extra == "dev"
Requires-Dist: ruff>=0.11.5; extra == "dev"
Requires-Dist: pytest>=8.3.5; extra == "dev"
Requires-Dist: pytest-cov>=6.1.1; extra == "dev"
